fluix/__init__.py
fluix/cli.py
fluix/cmds/anim_cmd.py
fluix/cmds/makepvd_cmd.py
fluix/cmds/optim_cmd.py
fluix/core/__init__.py
fluix/core/animate.py
fluix/core/makepvd.py
fluix/core/optimize_image.py
fluix/core/optimize_pdf.py
fluix/core/utils.py
fluix-0.1.4.dist-info/METADATA
fluix-0.1.4.dist-info/WHEEL
fluix-0.1.4.dist-info/entry_points.txt
fluix-0.1.4.dist-info/top_level.txt
fluix-0.1.4.dist-info/RECORD
