Metadata-Version: 2.4
Name: fluix
Version: 0.1.4
Summary: Python Post-Processing Toolkit for Scientific Visualization
Author-email: dhanushenoy <dhanushenoy@gmail.com>, dheerajshenoy <dheerajshenoy22@gmail.com>
Requires-Python: >=3.11
Requires-Dist: imageio[ffmpeg]
